india/__init__.py
india/cities.py
india/config.py
india/states.py
india/towns.py
india/utils.py
india/data/cities.csv
india/data/states.csv
india/data/towns.csv
india/data/ut.csv
pyindia-1.1.5.dist-info/LICENSE
pyindia-1.1.5.dist-info/METADATA
pyindia-1.1.5.dist-info/WHEEL
pyindia-1.1.5.dist-info/top_level.txt
pyindia-1.1.5.dist-info/RECORD
