Metadata-Version: 2.1
Name: pyindia
Version: 1.1.5
Summary: India's states and cities
Home-page: https://github.com/rishabhbatra10/in
Author: Rishabh Batra
Author-email: rishabhbatra1002@gmail.com
License: UNKNOWN
Platform: UNKNOWN
Classifier: Programming Language :: Python :: 3.7
Classifier: License :: OSI Approved :: MIT License
Classifier: Operating System :: OS Independent
